redl/__init__.py
redl/main.py
redl/utils.py
redl-0.1.2.dist-info/entry_points.txt
redl-0.1.2.dist-info/WHEEL
redl-0.1.2.dist-info/METADATA
redl-0.1.2.dist-info/RECORD
