Metadata-Version: 2.1
Name: redl
Version: 0.1.2
Summary: A cli to download reddit video along with audio
Home-page: https://github.com/amalshaji/redl
Author: Amal Shaji
Author-email: amalshajid@gmail.com
Requires-Python: >=3.6,<4.0
Classifier: Programming Language :: Python :: 3
Classifier: Programming Language :: Python :: 3.6
Classifier: Programming Language :: Python :: 3.7
Classifier: Programming Language :: Python :: 3.8
Classifier: Programming Language :: Python :: 3.9
Requires-Dist: requests (>=2.25.1,<3.0.0)
Requires-Dist: tqdm (>=4.56.0,<5.0.0)
Project-URL: Repository, https://github.com/amalshaji/redl
